leapfrog.py
leapfrog_env-1.1.0.dist-info/licenses/LICENSE
leapfrog_env-1.1.0.dist-info/METADATA
leapfrog_env-1.1.0.dist-info/WHEEL
leapfrog_env-1.1.0.dist-info/entry_points.txt
leapfrog_env-1.1.0.dist-info/top_level.txt
leapfrog_env-1.1.0.dist-info/RECORD
